articuno/__init__.py
articuno/backend_detect.py
articuno/codegen.py
articuno/dict_model.py
articuno/inference.py
articuno/iterable_infer.py
articuno/pandas_infer.py
articuno/polars_infer.py
articuno/pyspark_infer.py
articuno/sqlalchemy_infer.py
articuno/sqlmodel_infer.py
articuno-0.10.0.dist-info/METADATA
articuno-0.10.0.dist-info/WHEEL
articuno-0.10.0.dist-info/top_level.txt
articuno-0.10.0.dist-info/RECORD
