Metadata-Version: 2.4
Name: articuno
Version: 0.10.0
Summary: Convert Polars or Pandas DataFrames to lists of Pydantic models with schema inference
Author-email: Odos Matthews <odosmatthews@gmail.com>
Project-URL: Homepage, https://github.com/eddiethedean/articuno
Requires-Python: >=3.9
Requires-Dist: pydantic>=2.0
Requires-Dist: datamodel-code-generator>=0.24.0
Requires-Dist: genson
Provides-Extra: polars
Requires-Dist: polars>=0.20.0; extra == "polars"
Requires-Dist: poldantic>=0.2.1; extra == "polars"
Provides-Extra: pandas
Requires-Dist: pandas>=1.3; extra == "pandas"
Provides-Extra: sqlalchemy
Requires-Dist: sqlalchemy>=1.4; extra == "sqlalchemy"
Provides-Extra: sqlmodel
Requires-Dist: sqlmodel>=0.0.8; extra == "sqlmodel"
Provides-Extra: pyspark
Requires-Dist: pyspark>=3.0.0; extra == "pyspark"
Provides-Extra: dev
Requires-Dist: polars; extra == "dev"
Requires-Dist: pandas; extra == "dev"
Requires-Dist: pyarrow; extra == "dev"
Requires-Dist: sqlalchemy>=1.4; extra == "dev"
Requires-Dist: sqlmodel>=0.0.8; extra == "dev"
Requires-Dist: pyspark>=3.0.0; extra == "dev"
Requires-Dist: pytest>=7.0; extra == "dev"
Requires-Dist: build; extra == "dev"
Requires-Dist: twine; extra == "dev"
Requires-Dist: ruff; extra == "dev"
Requires-Dist: mypy; extra == "dev"
Provides-Extra: docs
Requires-Dist: sphinx; extra == "docs"
Requires-Dist: sphinx-autodoc-typehints; extra == "docs"
Requires-Dist: furo; extra == "docs"
